{
  "name": "Lettie Duncan",
  "age": 27,
  "address": {
    "street": "Boiho Road",
    "city": "Siapadog",
    "state": "WA",
    "zip": "57427"
  },
  "contact": {
    "phone": "(372) 518-4949",
    "servicePhone": "800418927"
  },
  "birthday": "1990-08-05T10:34:41.653Z",
  "ip": "74.216.39.210",
  "foo": "bar",
  "profile": {
    "about": "Ka pebdoj kume dawowa mivez ci ibogeh momgu kujalap idelimmi benap omraz ewa va lunawza zofo hubu ti. Kaeha co ekemikku vecalig si oraec wuet kawmew kirgadoc viv nejune hevano lawa eh me faczog pos oke. Momup izadomro ajuinakuw meg lenigagah uwbood lisnu tuvsoropi sunewho akomes ajoto co cicce. Ev fegozala huh zajus siselu looko wahusido neibuzow ul asi da moc dumbanu obifi.",
    "bio": "Lujona fatcomneb vuv turuezu ce ow jihkuszaz tipuk funegi likajo ozega il ju nag. Not vijweub gaowe uwu genobji cev zer izjib citubcac fip nun liupdoj meku volda. Fapaba fuwus fopono juwow cisjalto vipuwsuc kinez ivfizo mi uwe nusmu aki. Irjaw rebifav arvi inu gocuhuze opbav murojju ucuucuna bewemo cebibput cegcig aduti jeradlo itgib be ipihiw ojedowif. Gucanhew keseheeg mabo ginumer jugjaoh uhezuoc aknaz zorew zil evipi duowece pisfi nucvukupa ki nawpap lohdomu gakew. Riekupu sewiwkep vema mo icopi rocipzad zuvduviz robsizvob daivuidi vumleledu gojgi bawamrej bo zej."
  },
  "apiKey": "19aaf59613cee2cbed8496c7f2003d1986ef62c2661609e66d12d23761f50a97",
  "currency": {
    "code": "ETB",
    "name": "Ethiopia Birr"
  }
}