{
  "name": "Earl Cunningham",
  "age": 64,
  "address": {
    "street": "Mebat View",
    "city": "Roraihi",
    "state": "LA",
    "zip": "26152"
  },
  "contact": {
    "phone": "(856) 458-9293",
    "servicePhone": "800875291"
  },
  "birthday": "1981-10-27T03:05:01.720Z",
  "ip": "85.205.122.51",
  "foo": "bar",
  "profile": {
    "about": "Me naj tesmegka ujhepmar oj buvol jadafmag pacom jedre zafehoro rahke zaetedu ke sun gev raadcup hu cuetite. Asegaj saccabew pidozsof vupvonag ze gatarze mikuz wilje kaeze fo har siopu na dovfadu nafkopjaj pepis vuba hoffo. Piagina fedreshi efalees asho cim nuhobdoj zigfugiv no pifliztin iwa mozopcu nec. How owakekon koiro tad emuwoz octodiw ebnefok sifop iso kamaco uhelit taan. Tu wusugawo larfosdud ugveghop havrug jaw nomfuewa iwgalal samup jeb pu vumupbub widsukuni fencezik tama veldo meg jo.",
    "bio": "Suljopte ovuuf zotwujpe foj punu asi vu he potav gamupewuk gon za jecgakih vac. Cigeg bogeji nez ji irani aganiro ja mefo tugrazluf arped hi uzo zinogiko om wavehle juzeba ce. Aguewta ge mirjapuk mu uzewpu owali ulohebe nimfud posaf tiruuha des cu."
  },
  "apiKey": "6a67ff98705dcc1f40f249efbb96a1fec159c1240d3cd90a129bee6ed363c5cf",
  "currency": {
    "code": "BYR",
    "name": "Belarus Ruble"
  }
}